SimpleMaze_JJAP/__init__.py
SimpleMaze_JJAP/maze.py
SimpleMaze_JJAP-1.0.0.6.dist-info/METADATA
SimpleMaze_JJAP-1.0.0.6.dist-info/WHEEL
SimpleMaze_JJAP-1.0.0.6.dist-info/top_level.txt
SimpleMaze_JJAP-1.0.0.6.dist-info/RECORD
