Metadata-Version: 2.1
Name: SimpleMaze-JJAP
Version: 1.0.0.6
Summary: Simple Maze Module, made by JJAPDABOTTEAM
Home-page: https://github.com/Seol7523/SimpleMaze
Author: Seol7523
Author-email: seolchaehwan@naver.com
License: MIT
Platform: UNKNOWN
Requires-Python: >=3
